Metadata-Version: 2.4
Name: basic-colormath
Version: 1.1.1
Summary: Simple color conversion and perceptual (DeltaE CIE 2000) difference
Author: Shay Hill
Author-email: Shay Hill <shay_public@hotmail.com>
License-Expression: MIT
Requires-Python: >=3.10
